jacquard/__init__.py
jacquard/__main__.py
jacquard/expand.py
jacquard/jacquard.py
jacquard/merge.py
jacquard/summarize.py
jacquard/translate.py
jacquard/utils/__init__.py
jacquard/utils/command_validator.py
jacquard/utils/logger.py
jacquard/utils/summarize_rollup_transform.py
jacquard/utils/summarize_zscore_transform.py
jacquard/utils/utils.py
jacquard/utils/vcf.py
jacquard/variant_caller_transforms/__init__.py
jacquard/variant_caller_transforms/common_tags.py
jacquard/variant_caller_transforms/mutect.py
jacquard/variant_caller_transforms/strelka.py
jacquard/variant_caller_transforms/variant_caller_factory.py
jacquard/variant_caller_transforms/varscan.py
jacquard-1.1.5.dist-info/AUTHORS.rst
jacquard-1.1.5.dist-info/LICENSE
jacquard-1.1.5.dist-info/METADATA
jacquard-1.1.5.dist-info/WHEEL
jacquard-1.1.5.dist-info/entry_points.txt
jacquard-1.1.5.dist-info/top_level.txt
jacquard-1.1.5.dist-info/RECORD
