Metadata-Version: 2.1
Name: jacquard
Version: 1.1.5
Summary: Command-line tools to expedite analysis of Variant Call Format (VCF) files.
Home-page: https://github.com/umich-brcf-bioinf/Jacquard
Author: University of Michigan Bioinformatics Core
Author-email: bfx-jacquard@umich.edu
License: Apache
Keywords: VCF bioinformatic exome-seq DNA-seq variant-call-format
Platform: UNKNOWN
Classifier: Development Status :: 4 - Beta
Classifier: Environment :: Console
Classifier: Intended Audience :: Science/Research
Classifier: License :: OSI Approved :: Apache Software License
Classifier: Operating System :: OS Independent
Classifier: Programming Language :: Python :: 2.7
Classifier: Programming Language :: Python :: 3
Classifier: Topic :: Scientific/Engineering :: Bio-Informatics
Requires-Dist: natsort
